socfaker/__init__.py
socfaker/__main__.py
socfaker/agent.py
socfaker/alert.py
socfaker/alienvault.py
socfaker/alienvaultusm.py
socfaker/application.py
socfaker/azure.py
socfaker/azureproperties.py
socfaker/azurevm.py
socfaker/azurevmdetails.py
socfaker/azurevmmetrics.py
socfaker/azurevmmetricsproperties.py
socfaker/baseclass.py
socfaker/cloud.py
socfaker/computer.py
socfaker/container.py
socfaker/dns.py
socfaker/elastic.py
socfaker/elasticecs.py
socfaker/elasticecsfields.py
socfaker/elastichits.py
socfaker/email.py
socfaker/employee.py
socfaker/file.py
socfaker/http.py
socfaker/location.py
socfaker/logs.py
socfaker/logstreamer.py
socfaker/markdowntable.py
socfaker/network.py
socfaker/operatingsystem.py
socfaker/organization.py
socfaker/pcap.py
socfaker/process.py
socfaker/products.py
socfaker/qualysguard.py
socfaker/registry.py
socfaker/servicenow.py
socfaker/socfaker.py
socfaker/sysmon.py
socfaker/timestamp.py
socfaker/tls.py
socfaker/url.py
socfaker/useragent.py
socfaker/vulnerability.py
socfaker/vulnerabilityhost.py
socfaker/vulnerabilityscan.py
socfaker/windows.py
socfaker/windowseventdata.py
socfaker/windowseventlog.py
socfaker/windowseventsystem.py
socfaker/words.py
socfaker/data/alert_names.txt
socfaker/data/customers.txt
socfaker/data/email_x_headers.txt
socfaker/data/locations.json
socfaker/data/malicious_domains.txt
socfaker/data/malicious_hashes.txt
socfaker/data/malicious_ips.txt
socfaker/data/malicious_urls.txt
socfaker/data/mime_types.json
socfaker/data/nessus-plugin-samples.json
socfaker/data/tld.json
socfaker/data/uri.txt
socfaker/data/user_names.txt
socfaker/data/useragent.json
socfaker/data/windows-providers.txt
socfaker/data/words.txt
socfaker/data/filenames/bin_list.txt
socfaker/data/filenames/exe_list.txt
socfaker/data/filenames/program_files_x86_bin_list.txt
socfaker/data/filenames/program_files_x86_exe_list.txt
socfaker/data/filenames/sys_list.txt
socfaker/data/sysmon/10_process_access.txt
socfaker/data/sysmon/11_file_create.txt
soc_faker-4.0.2.dist-info/LICENSE.md
soc_faker-4.0.2.dist-info/METADATA
soc_faker-4.0.2.dist-info/WHEEL
soc_faker-4.0.2.dist-info/entry_points.txt
soc_faker-4.0.2.dist-info/top_level.txt
soc_faker-4.0.2.dist-info/RECORD
