Metadata-Version: 2.1
Name: soc-faker
Version: 4.0.2
Summary: A Python package to fake SOC (Security Operations Center) data
Home-page: https://github.com/swimlane/soc-faker
Author: Swimlane
Author-email: info@swimlane.com
License: MIT
Keywords: faker,soc,security,swimlane
Requires-Python: >=3.7, <4
License-File: LICENSE.md
Requires-Dist: requests (<3.0.0,>=2.28.0)
Requires-Dist: pendulum (<3.0.0,>=2.1.2)
Requires-Dist: ipaddress (<2.0.0,>=1.0.23)
Requires-Dist: bs4 (==0.0.1)
Requires-Dist: xmltodict (==0.12.0)
Requires-Dist: netaddr (==0.7.20)
Requires-Dist: fire (<0.5.0,>=0.4.0)
Requires-Dist: lorem-text (<3.0,>=2.1)
Requires-Dist: lxml (<5.0.0,>=4.6.3)
